fdsn_source_id.py
fdsn_source_id-0.0.1.dist-info/LICENSE
fdsn_source_id-0.0.1.dist-info/METADATA
fdsn_source_id-0.0.1.dist-info/WHEEL
fdsn_source_id-0.0.1.dist-info/top_level.txt
fdsn_source_id-0.0.1.dist-info/RECORD
