Metadata-Version: 2.1
Name: fdsn-source-id
Version: 0.0.1
Summary: A Python package for parsing and validating FDSN Source Identifiers
Author-email: Chad Trabant <chad.trabant@earthscope.org>, Adam Clark <adam.clark@earthscope.org>
License: Copyright (c) 2023 FDSN
Project-URL: Homepage, https://github.com/fdsn/fdsn-source-id-py
Classifier: Programming Language :: Python :: 3
Classifier: License :: OSI Approved :: MIT License
Classifier: Operating System :: OS Independent
Requires-Python: >=3.7
License-File: LICENSE
